mypkgwowlol/__init__.py
mypkgwowlol/mod1/__init__.py
mypkgwowlol/mod1/module1.py
mypkgwowlol/mod2/__init__.py
mypkgwowlol/mod2/module2.py
mypkgwowlol-0.4.8.dist-info/LICENSE.txt
mypkgwowlol-0.4.8.dist-info/METADATA
mypkgwowlol-0.4.8.dist-info/WHEEL
mypkgwowlol-0.4.8.dist-info/top_level.txt
mypkgwowlol-0.4.8.dist-info/RECORD
