Metadata-Version: 2.1
Name: mypkgwowlol
Version: 0.4.8
Summary: Describe your package in one sentence
Home-page: https://github.com/you/your_package
Author: You
Author-email: you@email.com
License: Apache License 2.0
Platform: UNKNOWN
License-File: LICENSE.txt
Requires-Dist: numpy
Requires-Dist: pandas
